{
  "info": {
    "_postman_id": "c79c321c-111e-4e35-a995-550863aebe65",
    "name": "Electronic Prescriptions Sandbox",
    "schema": "https://schema.getpostman.com/json/collection/v2.1.0/collection.json"
  },
  "item": [
    {
      "name": "Prescription POST Success",
      "event": [
        {
          "listen": "test",
          "script": {
            "id": "f91412e4-0dc0-41b3-9c22-f13a775234b0",
            "exec": [
              "const responseText = {\n    \"resourceType\": \"Binary\",\n    \"id\": \"79FDB414-FADE-459C-87E5-312E646A1910\",\n    \"contentType\": \"application/xml\",\n    \"data\": \"PEZyYWdtZW50c1RvQmVIYXNoZWQ+PEZyYWdtZW50Pjx0aW1lIHhtbG5zPSJ1cm46aGw3LW9yZzp2MyIgdmFsdWU9IjIwMDgwMjI3MTEzODAwIj48L3RpbWU+PGlkIHhtbG5zPSJ1cm46aGw3LW9yZzp2MyIgcm9vdD0iN0VCMDIzNDEtNUY2Mi00QTc2LTJDRDMtMzRGNTIzNDUyMzU2Ij48L2lkPjwvRnJhZ21lbnQ+PEZyYWdtZW50PjxBZ2VudFBlcnNvbiB4bWxucz0idXJuOmhsNy1vcmc6djMiIGNsYXNzQ29kZT0iQUdOVCI+PGlkIGV4dGVuc2lvbj0iMTI1Njg2NTQwMDI1IiByb290PSIxLjIuODI2LjAuMTI4NS4wLjIuMC42NyI+PC9pZD48Y29kZSBjb2RlPSJSMDI2MCIgY29kZVN5c3RlbT0iMS4yLjgyNi4wLjEyODUuMC4yLjEuMTA0Ij48L2NvZGU+PHRlbGVjb20gdXNlPSJXUCIgdmFsdWU9InRlbDowMTEzMjc1MzQyNTYiPjwvdGVsZWNvbT48YWdlbnRQZXJzb24gY2xhc3NDb2RlPSJQU04iIGRldGVybWluZXJDb2RlPSJJTlNUQU5DRSI+PGlkIGV4dGVuc2lvbj0iOTM0NTY1ODM4OTU2IiByb290PSIxLjIuODI2LjAuMTI4NS4wLjIuMC42NSI+PC9pZD48bmFtZT48cHJlZml4PkRyPC9wcmVmaXg+PGZhbWlseT5IdXJzdDwvZmFtaWx5PjwvbmFtZT48L2FnZW50UGVyc29uPjxyZXByZXNlbnRlZE9yZ2FuaXphdGlvbiBjbGFzc0NvZGU9Ik9SRyIgZGV0ZXJtaW5lckNvZGU9IklOU1RBTkNFIj48aWQgZXh0ZW5zaW9uPSJNODUwMTEiIHJvb3Q9IjEuMi44MjYuMC4xMjg1LjAuMS4xMCI+PC9pZD48Y29kZSBjb2RlPSIwMDEiIGNvZGVTeXN0ZW09IjIuMTYuODQwLjEuMTEzODgzLjIuMS4zLjIuNC4xNy45NCI+PC9jb2RlPjxuYW1lPlNpZ25pbmdfU3VyZ18xPC9uYW1lPjx0ZWxlY29tIHVzZT0iV1AiIHZhbHVlPSJ0ZWw6MDExMzI3NTQ1NjgiPjwvdGVsZWNvbT48YWRkciB1c2U9IldQIj48c3RyZWV0QWRkcmVzc0xpbmU+MSBQcmluY2VzIFN0cmVldDwvc3RyZWV0QWRkcmVzc0xpbmU+PHN0cmVldEFkZHJlc3NMaW5lPkxlZWRzPC9zdHJlZXRBZGRyZXNzTGluZT48cG9zdGFsQ29kZT5MUzEgNUFIPC9wb3N0YWxDb2RlPjwvYWRkcj48aGVhbHRoQ2FyZVByb3ZpZGVyTGljZW5zZSBjbGFzc0NvZGU9IlBST1YiPjxPcmdhbml6YXRpb24gY2xhc3NDb2RlPSJPUkciIGRldGVybWluZXJDb2RlPSJJTlNUQU5DRSI+PGlkIGV4dGVuc2lvbj0iNENEIiByb290PSIxLjIuODI2LjAuMTI4NS4wLjEuMTAiPjwvaWQ+PGNvZGUgY29kZT0iMDA1IiBjb2RlU3lzdGVtPSIyLjE2Ljg0MC4xLjExMzg4My4yLjEuMy4yLjQuMTcuOTQiPjwvY29kZT48bmFtZT5XZXN0ICAgICAgICAgWW9ya3NoaXJlPC9uYW1lPjwvT3JnYW5pemF0aW9uPjwvaGVhbHRoQ2FyZVByb3ZpZGVyTGljZW5zZT48L3JlcHJlc2VudGVkT3JnYW5pemF0aW9uPjwvQWdlbnRQZXJzb24+PC9GcmFnbWVudD48RnJhZ21lbnQ+PHJlY29yZFRhcmdldCB4bWxucz0idXJuOmhsNy1vcmc6djMiIHR5cGVDb2RlPSJSQ1QiPjxQYXRpZW50IGNsYXNzQ29kZT0iUEFUIj48aWQgZXh0ZW5zaW9uPSI5OTAwMDA4NDY0IiByb290PSIyLjE2Ljg0MC4xLjExMzg4My4yLjEuNC4xIj48L2lkPjxhZGRyIHVzZT0iSCI+PHN0cmVldEFkZHJlc3NMaW5lPjEgICAgT3RsZXkgUm9hZCw8L3N0cmVldEFkZHJlc3NMaW5lPjxzdHJlZXRBZGRyZXNzTGluZT5MZWVkczwvc3RyZWV0QWRkcmVzc0xpbmU+PHBvc3RhbENvZGU+TFM2IDVSVTwvcG9zdGFsQ29kZT48L2FkZHI+PHBhdGllbnRQZXJzb24gY2xhc3NDb2RlPSJQU04iIGRldGVybWluZXJDb2RlPSJJTlNUQU5DRSI+PG5hbWU+PHByZWZpeD5NcjwvcHJlZml4PjxnaXZlbj5NaWNoYWVsPC9naXZlbj48Z2l2ZW4+SmFjazwvZ2l2ZW4+PGZhbWlseT5BbmRlcnNvbjwvZmFtaWx5PjwvbmFtZT48YWRtaW5pc3RyYXRpdmVHZW5kZXJDb2RlIGNvZGU9IjEiIGNvZGVTeXN0ZW09IjIuMTYuODQwLjEuMTEzODgzLjIuMS4zLjIuNC4xNi4yNSI+PC9hZG1pbmlzdHJhdGl2ZUdlbmRlckNvZGU+PGJpcnRoVGltZSB2YWx1ZT0iMTk3MzA0MjEiPjwvYmlydGhUaW1lPjxwbGF5ZWRQcm92aWRlclBhdGllbnQgY2xhc3NDb2RlPSJQQVQiPjxzdWJqZWN0T2YgdHlwZUNvZGU9IlNCSiI+PHBhdGllbnRDYXJlUHJvdmlzaW9uIGNsYXNzQ29kZT0iUENQUiIgbW9vZENvZGU9IkVWTiI+PGNvZGUgY29kZT0iMSIgY29kZVN5c3RlbT0iMi4xNi44NDAuMS4xMTM4ODMuMi4xLjMuMi40LjE3LjM3Ij48L2NvZGU+PHJlc3BvbnNpYmxlUGFydHkgdHlwZUNvZGU9IlJFU1AiPjxoZWFsdGhDYXJlUHJvdmlkZXIgY2xhc3NDb2RlPSJQUk9WIj48aWQgZXh0ZW5zaW9uPSIxMDAwMDQiIHJvb3Q9IjEuMi44MjYuMC4xMjg1LjAuMi4wLjY1Ij48L2lkPjwvaGVhbHRoQ2FyZVByb3ZpZGVyPjwvcmVzcG9uc2libGVQYXJ0eT48L3BhdGllbnRDYXJlUHJvdmlzaW9uPjwvc3ViamVjdE9mPjwvcGxheWVkUHJvdmlkZXJQYXRpZW50PjwvcGF0aWVudFBlcnNvbj48L1BhdGllbnQ+PC9yZWNvcmRUYXJnZXQ+PC9GcmFnbWVudD48RnJhZ21lbnQ+PHBlcnRpbmVudExpbmVJdGVtIHhtbG5zPSJ1cm46aGw3LW9yZzp2MyIgY2xhc3NDb2RlPSJTQkFETSIgbW9vZENvZGU9IlJRTyI+PGlkIHJvb3Q9IjdCMzhERTMyLTg3N0YtNkQ1My1EMjdDLTg2RTFCQTM1MDE2QyI+PC9pZD48Y29kZSBjb2RlPSIxODYyOTAwNSIgY29kZVN5c3RlbT0iMi4xNi44NDAuMS4xMTM4ODMuMi4xLjMuMi40LjE1IiBkaXNwbGF5TmFtZT0iTWVkaWNhbCBBZG1pbmlzdHJhdGlvbiI+PC9jb2RlPjxlZmZlY3RpdmVUaW1lIG51bGxGbGF2b3I9Ik5BIj48L2VmZmVjdGl2ZVRpbWU+PHByb2R1Y3QgY29udGV4dENvbnRyb2xDb2RlPSJPUCIgdHlwZUNvZGU9IlBSRCI+PG1hbnVmYWN0dXJlZFByb2R1Y3QgY2xhc3NDb2RlPSJNQU5VIj48bWFudWZhY3R1cmVkUmVxdWVzdGVkTWF0ZXJpYWwgY2xhc3NDb2RlPSJNTUFUIiBkZXRlcm1pbmVyQ29kZT0iS0lORCI+PGNvZGUgY29kZT0iMzE3ODk2MDA2IiBjb2RlU3lzdGVtPSIyLjE2Ljg0MC4xLjExMzg4My4yLjEuMy4yLjQuMTUiIGRpc3BsYXlOYW1lPSJkaWdveGluIHRhYmxldHMgMTI1bWljcm9ncmFtcyI+PC9jb2RlPjwvbWFudWZhY3R1cmVkUmVxdWVzdGVkTWF0ZXJpYWw+PC9tYW51ZmFjdHVyZWRQcm9kdWN0PjwvcHJvZHVjdD48Y29tcG9uZW50IHR5cGVDb2RlPSJDT01QIj48c2VwZXJhdGFibGVJbmQgdmFsdWU9ImZhbHNlIj48L3NlcGVyYXRhYmxlSW5kPjxsaW5lSXRlbVF1YW50aXR5IGNsYXNzQ29kZT0iU1BMWSIgbW9vZENvZGU9IlJRTyI+PGNvZGU+PC9jb2RlPjxxdWFudGl0eSB1bml0PSIxIiB2YWx1ZT0iMjgiPjx0cmFuc2xhdGlvbiBjb2RlPSIzMzE5NDExMDAwMDAxMTA5IiBjb2RlU3lzdGVtPSIyLjE2Ljg0MC4xLjExMzg4My4yLjEuMy4yLjQuMTUiIGRpc3BsYXlOYW1lPSJ0YWJsZXQiIHZhbHVlPSIyOCI+PC90cmFuc2xhdGlvbj48L3F1YW50aXR5PjwvbGluZUl0ZW1RdWFudGl0eT48L2NvbXBvbmVudD48cGVydGluZW50SW5mb3JtYXRpb24yIGNvbnRleHRDb25kdWN0aW9uSW5kPSJ0cnVlIiB0eXBlQ29kZT0iUEVSVCI+PHNlcGVyYXRhYmxlSW5kIHZhbHVlPSJmYWxzZSI+PC9zZXBlcmF0YWJsZUluZD48cGVydGluZW50RG9zYWdlSW5zdHJ1Y3Rpb25zIGNsYXNzQ29kZT0iT0JTIiBtb29kQ29kZT0iRVZOIj48Y29kZSBjb2RlPSJESSIgY29kZVN5c3RlbT0iMi4xNi44NDAuMS4xMTM4ODMuMi4xLjMuMi40LjE3LjMwIj48L2NvZGU+PHZhbHVlPjEgdGFibGV0IGFmdGVyIGJyZWFrZmFzdDwvdmFsdWU+PC9wZXJ0aW5lbnREb3NhZ2VJbnN0cnVjdGlvbnM+PC9wZXJ0aW5lbnRJbmZvcm1hdGlvbjI+PC9wZXJ0aW5lbnRMaW5lSXRlbT48L0ZyYWdtZW50PjxGcmFnbWVudD48cGVydGluZW50TGluZUl0ZW0geG1sbnM9InVybjpobDctb3JnOnYzIiBjbGFzc0NvZGU9IlNCQURNIiBtb29kQ29kZT0iUlFPIj48aWQgcm9vdD0iOEQxMkRFNjItODI2Ri04RDMyLUUxN0MtODZEM0JBNTYwMTNFIj48L2lkPjxjb2RlIGNvZGU9IjE4NjI5MDA1IiBjb2RlU3lzdGVtPSIyLjE2Ljg0MC4xLjExMzg4My4yLjEuMy4yLjQuMTUiIGRpc3BsYXlOYW1lPSJNZWRpY2FsIEFkbWluaXN0cmF0aW9uIj48L2NvZGU+PGVmZmVjdGl2ZVRpbWUgbnVsbEZsYXZvcj0iTkEiPjwvZWZmZWN0aXZlVGltZT48cHJvZHVjdCBjb250ZXh0Q29udHJvbENvZGU9Ik9QIiB0eXBlQ29kZT0iUFJEIj48bWFudWZhY3R1cmVkUHJvZHVjdCBjbGFzc0NvZGU9Ik1BTlUiPjxtYW51ZmFjdHVyZWRSZXF1ZXN0ZWRNYXRlcmlhbCBjbGFzc0NvZGU9Ik1NQVQiIGRldGVybWluZXJDb2RlPSJLSU5EIj48Y29kZSBjb2RlPSIzMTk3NzUwMDQiIGNvZGVTeXN0ZW09IjIuMTYuODQwLjEuMTEzODgzLjIuMS4zLjIuNC4xNSIgZGlzcGxheU5hbWU9ImFzcGlyaW4gdGFibGV0cyA3NW1nIj48L2NvZGU+PC9tYW51ZmFjdHVyZWRSZXF1ZXN0ZWRNYXRlcmlhbD48L21hbnVmYWN0dXJlZFByb2R1Y3Q+PC9wcm9kdWN0Pjxjb21wb25lbnQgdHlwZUNvZGU9IkNPTVAiPjxzZXBlcmF0YWJsZUluZCB2YWx1ZT0iZmFsc2UiPjwvc2VwZXJhdGFibGVJbmQ+PGxpbmVJdGVtUXVhbnRpdHkgY2xhc3NDb2RlPSJTUExZIiBtb29kQ29kZT0iUlFPIj48Y29kZT48L2NvZGU+PHF1YW50aXR5IHVuaXQ9IjEiIHZhbHVlPSIyOCI+PHRyYW5zbGF0aW9uIGNvZGU9IjMzMTk0MTEwMDAwMDExMDkiIGNvZGVTeXN0ZW09IjIuMTYuODQwLjEuMTEzODgzLjIuMS4zLjIuNC4xNSIgZGlzcGxheU5hbWU9InRhYmxldCIgdmFsdWU9IjI4Ij48L3RyYW5zbGF0aW9uPjwvcXVhbnRpdHk+PC9saW5lSXRlbVF1YW50aXR5PjwvY29tcG9uZW50PjxwZXJ0aW5lbnRJbmZvcm1hdGlvbjIgY29udGV4dENvbmR1Y3Rpb25JbmQ9InRydWUiIHR5cGVDb2RlPSJQRVJUIj48c2VwZXJhdGFibGVJbmQgdmFsdWU9ImZhbHNlIj48L3NlcGVyYXRhYmxlSW5kPjxwZXJ0aW5lbnREb3NhZ2VJbnN0cnVjdGlvbnMgY2xhc3NDb2RlPSJPQlMiIG1vb2RDb2RlPSJFVk4iPjxjb2RlIGNvZGU9IkRJIiBjb2RlU3lzdGVtPSIyLjE2Ljg0MC4xLjExMzg4My4yLjEuMy4yLjQuMTcuMzAiPjwvY29kZT48dmFsdWU+MSB0YWJsZXQgZHVyaW5nIGJyZWFrZmFzdDwvdmFsdWU+PC9wZXJ0aW5lbnREb3NhZ2VJbnN0cnVjdGlvbnM+PC9wZXJ0aW5lbnRJbmZvcm1hdGlvbjI+PC9wZXJ0aW5lbnRMaW5lSXRlbT48L0ZyYWdtZW50PjxGcmFnbWVudD48cGVydGluZW50TGluZUl0ZW0geG1sbnM9InVybjpobDctb3JnOnYzIiBjbGFzc0NvZGU9IlNCQURNIiBtb29kQ29kZT0iUlFPIj48aWQgcm9vdD0iOUExMkRFNjItODI2Ri04RDMyLUUxN0MtODZEM0JBNTYwMjNGIj48L2lkPjxjb2RlIGNvZGU9IjE4NjI5MDA1IiBjb2RlU3lzdGVtPSIyLjE2Ljg0MC4xLjExMzg4My4yLjEuMy4yLjQuMTUiIGRpc3BsYXlOYW1lPSJNZWRpY2FsIEFkbWluaXN0cmF0aW9uIj48L2NvZGU+PGVmZmVjdGl2ZVRpbWUgbnVsbEZsYXZvcj0iTkEiPjwvZWZmZWN0aXZlVGltZT48cHJvZHVjdCBjb250ZXh0Q29udHJvbENvZGU9Ik9QIiB0eXBlQ29kZT0iUFJEIj48bWFudWZhY3R1cmVkUHJvZHVjdCBjbGFzc0NvZGU9Ik1BTlUiPjxtYW51ZmFjdHVyZWRSZXF1ZXN0ZWRNYXRlcmlhbCBjbGFzc0NvZGU9Ik1NQVQiIGRldGVybWluZXJDb2RlPSJLSU5EIj48Y29kZSBjb2RlPSIzNzcxNDUwMDUiIGNvZGVTeXN0ZW09IjIuMTYuODQwLjEuMTEzODgzLjIuMS4zLjIuNC4xNSIgZGlzcGxheU5hbWU9IkxvcmF6ZXBhbSAyIG1nIG9yYWwgdGFibGV0Ij48L2NvZGU+PC9tYW51ZmFjdHVyZWRSZXF1ZXN0ZWRNYXRlcmlhbD48L21hbnVmYWN0dXJlZFByb2R1Y3Q+PC9wcm9kdWN0Pjxjb21wb25lbnQgdHlwZUNvZGU9IkNPTVAiPjxzZXBlcmF0YWJsZUluZCB2YWx1ZT0iZmFsc2UiPjwvc2VwZXJhdGFibGVJbmQ+PGxpbmVJdGVtUXVhbnRpdHkgY2xhc3NDb2RlPSJTUExZIiBtb29kQ29kZT0iUlFPIj48Y29kZT48L2NvZGU+PHF1YW50aXR5IHVuaXQ9IjEiIHZhbHVlPSI4NCI+PHRyYW5zbGF0aW9uIGNvZGU9IjMzMTk0MTEwMDAwMDExMDkiIGNvZGVTeXN0ZW09IjIuMTYuODQwLjEuMTEzODgzLjIuMS4zLjIuNC4xNSIgZGlzcGxheU5hbWU9InRhYmxldCIgdmFsdWU9Ijg0Ij48L3RyYW5zbGF0aW9uPjwvcXVhbnRpdHk+PC9saW5lSXRlbVF1YW50aXR5PjwvY29tcG9uZW50PjxwZXJ0aW5lbnRJbmZvcm1hdGlvbjIgY29udGV4dENvbmR1Y3Rpb25JbmQ9InRydWUiIHR5cGVDb2RlPSJQRVJUIj48c2VwZXJhdGFibGVJbmQgdmFsdWU9ImZhbHNlIj48L3NlcGVyYXRhYmxlSW5kPjxwZXJ0aW5lbnREb3NhZ2VJbnN0cnVjdGlvbnMgY2xhc3NDb2RlPSJPQlMiIG1vb2RDb2RlPSJFVk4iPjxjb2RlIGNvZGU9IkRJIiBjb2RlU3lzdGVtPSIyLjE2Ljg0MC4xLjExMzg4My4yLjEuMy4yLjQuMTcuMzAiPjwvY29kZT48dmFsdWU+MyB0YWJsZXRzIGJlZm9yZSBicmVha2Zhc3Q8L3ZhbHVlPjwvcGVydGluZW50RG9zYWdlSW5zdHJ1Y3Rpb25zPjwvcGVydGluZW50SW5mb3JtYXRpb24yPjwvcGVydGluZW50TGluZUl0ZW0+PC9GcmFnbWVudD48RnJhZ21lbnQ+PHBlcnRpbmVudExpbmVJdGVtIHhtbG5zPSJ1cm46aGw3LW9yZzp2MyIgY2xhc3NDb2RlPSJTQkFETSIgbW9vZENvZGU9IlJRTyI+PGlkIHJvb3Q9IjJBMzJERTYyLTgyNkYtOEQzMi1FMTdDLTg2RDNCQTU2MDEzRCI+PC9pZD48Y29kZSBjb2RlPSIxODYyOTAwNSIgY29kZVN5c3RlbT0iMi4xNi44NDAuMS4xMTM4ODMuMi4xLjMuMi40LjE1IiBkaXNwbGF5TmFtZT0iTWVkaWNhbCBBZG1pbmlzdHJhdGlvbiI+PC9jb2RlPjxlZmZlY3RpdmVUaW1lIG51bGxGbGF2b3I9Ik5BIj48L2VmZmVjdGl2ZVRpbWU+PHByb2R1Y3QgY29udGV4dENvbnRyb2xDb2RlPSJPUCIgdHlwZUNvZGU9IlBSRCI+PG1hbnVmYWN0dXJlZFByb2R1Y3QgY2xhc3NDb2RlPSJNQU5VIj48bWFudWZhY3R1cmVkUmVxdWVzdGVkTWF0ZXJpYWwgY2xhc3NDb2RlPSJNTUFUIiBkZXRlcm1pbmVyQ29kZT0iS0lORCI+PGNvZGUgY29kZT0iNDIxMzc1MDA0IiBjb2RlU3lzdGVtPSIyLjE2Ljg0MC4xLjExMzg4My4yLjEuMy4yLjQuMTUiIGRpc3BsYXlOYW1lPSJDaXRhbG9wcmFtIChhcyBjaXRhbG9wcmFtIGh5ZHJvYnJvbWlkZSkgNDAgbWcgb3JvZGlzcGVyc2libGUgdGFibGV0Ij48L2NvZGU+PC9tYW51ZmFjdHVyZWRSZXF1ZXN0ZWRNYXRlcmlhbD48L21hbnVmYWN0dXJlZFByb2R1Y3Q+PC9wcm9kdWN0Pjxjb21wb25lbnQgdHlwZUNvZGU9IkNPTVAiPjxzZXBlcmF0YWJsZUluZCB2YWx1ZT0iZmFsc2UiPjwvc2VwZXJhdGFibGVJbmQ+PGxpbmVJdGVtUXVhbnRpdHkgY2xhc3NDb2RlPSJTUExZIiBtb29kQ29kZT0iUlFPIj48Y29kZT48L2NvZGU+PHF1YW50aXR5IHVuaXQ9IjEiIHZhbHVlPSI1NiI+PHRyYW5zbGF0aW9uIGNvZGU9IjMzMTk0MTEwMDAwMDExMDkiIGNvZGVTeXN0ZW09IjIuMTYuODQwLjEuMTEzODgzLjIuMS4zLjIuNC4xNSIgZGlzcGxheU5hbWU9InRhYmxldCIgdmFsdWU9IjU2Ij48L3RyYW5zbGF0aW9uPjwvcXVhbnRpdHk+PC9saW5lSXRlbVF1YW50aXR5PjwvY29tcG9uZW50PjxwZXJ0aW5lbnRJbmZvcm1hdGlvbjIgY29udGV4dENvbmR1Y3Rpb25JbmQ9InRydWUiIHR5cGVDb2RlPSJQRVJUIj48c2VwZXJhdGFibGVJbmQgdmFsdWU9ImZhbHNlIj48L3NlcGVyYXRhYmxlSW5kPjxwZXJ0aW5lbnREb3NhZ2VJbnN0cnVjdGlvbnMgY2xhc3NDb2RlPSJPQlMiIG1vb2RDb2RlPSJFVk4iPjxjb2RlIGNvZGU9IkRJIiBjb2RlU3lzdGVtPSIyLjE2Ljg0MC4xLjExMzg4My4yLjEuMy4yLjQuMTcuMzAiPjwvY29kZT48dmFsdWU+MiB0YWJsZXRzIGFmdGVyIGJyZWFrZmFzdDwvdmFsdWU+PC9wZXJ0aW5lbnREb3NhZ2VJbnN0cnVjdGlvbnM+PC9wZXJ0aW5lbnRJbmZvcm1hdGlvbjI+PC9wZXJ0aW5lbnRMaW5lSXRlbT48L0ZyYWdtZW50PjwvRnJhZ21lbnRzVG9CZUhhc2hlZD4=\"\n}",
              "pm.test(\"Status code is 200\", function () {",
              "    pm.response.to.have.status(200);",
              "});",
              "pm.test(\"Body is correct\", function () {",
              "    pm.response.to.have.body(responseText);",
              "});"
            ],
            "type": "text/javascript"
          }
        }
      ],
      "request": {
        "auth": {
          "type": "oauth2",
          "oauth2": [
            {
              "key": "accessToken",
              "value": "",
              "type": "string"
            },
            {
              "key": "tokenType",
              "value": "Bearer",
              "type": "string"
            },
            {
              "key": "addTokenTo",
              "value": "header",
              "type": "string"
            }
          ]
        },
        "method": "POST",
        "header": [
          {
            "key": "NHSD-Session-URID",
            "value": "123",
            "type": "text"
          }
        ],
        "body": {
          "mode": "raw",
          "raw": "{\n  \"resourceType\": \"Bundle\",\n  \"id\": \"79FDB414-FADE-459C-87E5-312E646A1910\",\n  \"identifier\":\n  {\n    \"system\": \"urn:oid:2.16.840.1.113883.2.1.3.2.4.18.8\",\n    \"value\": \"2BE1EA-L36920-0353AW\"\n  },\n  \"type\": \"collection\",\n  \"entry\": [\n    {\n      \"fullUrl\": \"urn:uuid:7B38DE32-877F-6D53-D27C-86E1BA35016C\",\n      \"resource\": {\n        \"resourceType\": \"MedicationRequest\",\n        \"id\": \"7B38DE32-877F-6D53-D27C-86E1BA35016C\",\n        \"status\": \"active\",\n        \"intent\": \"order\",\n        \"medicationCodeableConcept\": {\n          \"coding\": [\n            {\n              \"system\": \"http://snomed.info/sct\",\n              \"code\": \"317896006\",\n              \"display\": \"Digoxin 125 microgram oral tablet\"\n            }\n          ]\n        },\n        \"subject\": {\n          \"reference\": \"urn:uuid:C6750CAA-3CA9-4F29-A282-6EE1AA5D7D4C\"\n        },\n        \"encounter\": {\n          \"reference\": \"urn:uuid:401AEEE1-0E1B-42A0-989C-03DEA8667CB7\"\n        },\n        \"authoredOn\": \"2008-02-27T11:38:00.000+00:00\",\n        \"requester\": {\n          \"reference\": \"urn:uuid:1557E58E-3B1E-41DD-B3B5-D4D393DC5A3D\"\n        },\n        \"dosageInstruction\": [\n          {\n            \"text\": \"1 tablet after breakfast\"\n          }\n        ],\n        \"dispenseRequest\": {\n          \"quantity\": {\n            \"value\": 28,\n            \"unit\": \"tablet\",\n            \"system\": \"http://snomed.info/sct\",\n            \"code\": \"3319411000001109\"\n          }\n        }\n      }\n    },\n    {\n      \"fullUrl\": \"urn:uuid:8D12DE62-826F-8D32-E17C-86D3BA56013E\",\n      \"resource\": {\n        \"resourceType\": \"MedicationRequest\",\n        \"id\": \"8D12DE62-826F-8D32-E17C-86D3BA56013E\",\n        \"status\": \"active\",\n        \"intent\": \"order\",\n        \"medicationCodeableConcept\": {\n          \"coding\": [\n            {\n              \"system\": \"http://snomed.info/sct\",\n              \"code\": \"319775004\",\n              \"display\": \"Aspirin 75 mg oral tablet\"\n            }\n          ]\n        },\n        \"subject\": {\n          \"reference\": \"urn:uuid:C6750CAA-3CA9-4F29-A282-6EE1AA5D7D4C\"\n        },\n        \"encounter\": {\n          \"reference\": \"urn:uuid:401AEEE1-0E1B-42A0-989C-03DEA8667CB7\"\n        },\n        \"authoredOn\": \"2008-02-27T11:38:00.000+00:00\",\n        \"requester\": {\n          \"reference\": \"urn:uuid:1557E58E-3B1E-41DD-B3B5-D4D393DC5A3D\"\n        },\n        \"dosageInstruction\": [\n          {\n            \"text\": \"1 tablet during breakfast\"\n          }\n        ],\n        \"dispenseRequest\": {\n          \"quantity\": {\n            \"value\": 28,\n            \"unit\": \"tablet\",\n            \"system\": \"http://snomed.info/sct\",\n            \"code\": \"3319411000001109\"\n          }\n        }\n      }\n    },\n    {\n      \"fullUrl\": \"urn:uuid:9A12DE62-826F-8D32-E17C-86D3BA56023F\",\n      \"resource\": {\n        \"resourceType\": \"MedicationRequest\",\n        \"id\": \"9A12DE62-826F-8D32-E17C-86D3BA56023F\",\n        \"status\": \"active\",\n        \"intent\": \"order\",\n        \"medicationCodeableConcept\": {\n          \"coding\": [\n            {\n              \"system\": \"http://snomed.info/sct\",\n              \"code\": \"377145005\",\n              \"display\": \"Lorazepam 2 mg oral tablet\"\n            }\n          ]\n        },\n        \"subject\": {\n          \"reference\": \"urn:uuid:C6750CAA-3CA9-4F29-A282-6EE1AA5D7D4C\"\n        },\n        \"encounter\": {\n          \"reference\": \"urn:uuid:401AEEE1-0E1B-42A0-989C-03DEA8667CB7\"\n        },\n        \"authoredOn\": \"2008-02-27T11:38:00.000+00:00\",\n        \"requester\": {\n          \"reference\": \"urn:uuid:1557E58E-3B1E-41DD-B3B5-D4D393DC5A3D\"\n        },\n        \"dosageInstruction\": [\n          {\n            \"text\": \"3 tablets before breakfast\"\n          }\n        ],\n        \"dispenseRequest\": {\n          \"quantity\": {\n            \"value\": 84,\n            \"unit\": \"tablet\",\n            \"system\": \"http://snomed.info/sct\",\n            \"code\": \"3319411000001109\"\n          }\n        }\n      }\n    },\n    {\n      \"fullUrl\": \"urn:uuid:2A32DE62-826F-8D32-E17C-86D3BA56013D\",\n      \"resource\": {\n        \"resourceType\": \"MedicationRequest\",\n        \"id\": \"2A32DE62-826F-8D32-E17C-86D3BA56013D\",\n        \"status\": \"active\",\n        \"intent\": \"order\",\n        \"medicationCodeableConcept\": {\n          \"coding\": [\n            {\n              \"system\": \"http://snomed.info/sct\",\n              \"code\": \"421375004\",\n              \"display\": \"Citalopram (as citalopram hydrobromide) 40 mg orodispersible tablet\"\n            }\n          ]\n        },\n        \"subject\": {\n          \"reference\": \"urn:uuid:C6750CAA-3CA9-4F29-A282-6EE1AA5D7D4C\"\n        },\n        \"encounter\": {\n          \"reference\": \"urn:uuid:401AEEE1-0E1B-42A0-989C-03DEA8667CB7\"\n        },\n        \"authoredOn\": \"2008-02-27T11:38:00.000+00:00\",\n        \"requester\": {\n          \"reference\": \"urn:uuid:1557E58E-3B1E-41DD-B3B5-D4D393DC5A3D\"\n        },\n        \"dosageInstruction\": [\n          {\n            \"text\": \"2 tablets after breakfast\"\n          }\n        ],\n        \"dispenseRequest\": {\n          \"quantity\": {\n            \"value\": 56,\n            \"unit\": \"tablet\",\n            \"system\": \"http://snomed.info/sct\",\n            \"code\": \"3319411000001109\"\n          }\n        }\n      }\n    },\n    {\n      \"fullUrl\": \"urn:uuid:C6750CAA-3CA9-4F29-A282-6EE1AA5D7D4C\",\n      \"resource\": {\n        \"resourceType\": \"Patient\",\n        \"id\": \"C6750CAA-3CA9-4F29-A282-6EE1AA5D7D4C\",\n        \"identifier\": [\n          {\n            \"system\": \"https://fhir.nhs.uk/Id/nhs-number\",\n            \"value\": \"9900008464\"\n          }\n        ],\n        \"name\": [\n          {\n            \"use\": \"official\",\n            \"family\": \"Anderson\",\n            \"given\": [\n              \"Michael\",\n              \"Jack\"\n            ],\n            \"prefix\": [\n              \"Mr\"\n            ]\n          }\n        ],\n        \"gender\": \"male\",\n        \"birthDate\": \"1973-04-21\",\n        \"address\": [\n          {\n            \"use\": \"home\",\n            \"type\": \"both\",\n            \"line\": [\n              \"1 Otley Road,\"\n            ],\n            \"city\": \"Leeds\",\n            \"postalCode\": \"LS6 5RU\"\n          }\n        ]\n      }\n    },\n    {\n      \"fullUrl\": \"urn:uuid:1557E58E-3B1E-41DD-B3B5-D4D393DC5A3D\",\n      \"resource\": {\n        \"resourceType\": \"Practitioner\",\n        \"id\": \"1557E58E-3B1E-41DD-B3B5-D4D393DC5A3D\",\n        \"identifier\": [\n          {\n            \"system\": \"https://fhir.nhs.uk/Id/sds-user-id\",\n            \"value\": \"125686540025\"\n          },\n          {\n            \"system\": \"https://fhir.nhs.uk/Id/sds-job-role-id\",\n            \"value\": \"R0260\"\n          },\n          {\n            \"system\": \"https://fhir.nhs.uk/Id/sds-role-profile-id\",\n            \"value\": \"934565838956\"\n          }\n        ],\n        \"name\": [\n          {\n            \"use\": \"official\",\n            \"family\": \"Hurst\",\n            \"prefix\": [\n              \"Dr\"\n            ]\n          }\n        ],\n        \"telecom\": [\n          {\n            \"system\": \"phone\",\n            \"value\": \"tel:011327534256\",\n            \"use\": \"work\"\n          }\n        ]\n      }\n    },\n    {\n      \"fullUrl\": \"urn:uuid:401AEEE1-0E1B-42A0-989C-03DEA8667CB7\",\n      \"resource\": {\n        \"resourceType\": \"Encounter\",\n        \"id\": \"401AEEE1-0E1B-42A0-989C-03DEA8667CB7\",\n        \"status\": \"finished\",\n        \"class\": {\n          \"system\": \"http://terminology.hl7.org/CodeSystem/v3-ActCode\",\n          \"code\": \"AMB\"\n        },\n        \"serviceProvider\": {\n          \"reference\": \"urn:uuid:6666C3B3-FDCD-41B8-9D69-AD1E6D99D9FC\"\n        }\n      }\n    },\n    {\n      \"fullUrl\": \"urn:uuid:6666C3B3-FDCD-41B8-9D69-AD1E6D99D9FC\",\n      \"resource\": {\n        \"resourceType\": \"Organization\",\n        \"id\": \"6666C3B3-FDCD-41B8-9D69-AD1E6D99D9FC\",\n        \"identifier\": [\n          {\n            \"system\": \"https://fhir.nhs.uk/Id/ods-organization-code\",\n            \"value\": \"M85011\"\n          }\n        ],\n        \"type\": [\n          {\n            \"coding\": [\n              {\n                \"system\": \"urn:oid:2.16.840.1.113883.2.1.3.2.4.17.94\",\n                \"code\": \"001\",\n                \"display\": \"General Medical Practice\"\n              }\n            ]\n          }\n        ],\n        \"name\": \"Signing_Surg_1\",\n        \"telecom\": [\n          {\n            \"system\": \"phone\",\n            \"value\": \"tel:01132754568\",\n            \"use\": \"work\"\n          }\n        ],\n        \"address\": [\n          {\n            \"use\": \"work\",\n            \"line\": [\n              \"1 Princes Street\"\n            ],\n            \"city\": \"Leeds\",\n            \"postalCode\": \"LS1 5AH\"\n          }\n        ],\n        \"partOf\": {\n          \"reference\": \"urn:uuid:8DCB2153-09F5-4604-9229-A5C8C7195199\"\n        }\n      }\n    },\n    {\n      \"fullUrl\": \"urn:uuid:8DCB2153-09F5-4604-9229-A5C8C7195199\",\n      \"resource\": {\n        \"resourceType\": \"Organization\",\n        \"id\": \"8DCB2153-09F5-4604-9229-A5C8C7195199\",\n        \"identifier\": [\n          {\n            \"system\": \"https://fhir.nhs.uk/Id/ods-organization-code\",\n            \"value\": \"4CD\"\n          }\n        ],\n        \"type\": [\n          {\n            \"coding\": [\n              {\n                \"system\": \"urn:oid:2.16.840.1.113883.2.1.3.2.4.17.94\",\n                \"code\": \"005\",\n                \"display\": \"Primary Care Trust\"\n              }\n            ]\n          }\n        ],\n        \"name\": \"West Yorkshire\"\n      }\n    }\n  ]\n}",
          "options": {
            "raw": {
              "language": "json"
            }
          }
        },
        "url": {
          "raw": "{{base_url}}/Prescription",
          "host": [
            "{{base_url}}"
          ],
          "path": [
            "Prescription"
          ]
        }
      },
      "response": []
    },
    {
      "name": "Prescription PUT Success",
      "event": [
        {
          "listen": "test",
          "script": {
            "id": "2f45b9f9-4e1c-4c6c-90fd-b884a223d8ca",
            "exec": [
              "const responseText = {\n    \"resourceType\": \"Bundle\",\n    \"id\": \"E8E8D623-62C9-4642-BC51-AB50430DF8CA\",\n    \"type\": \"collection\",\n    \"entry\": [\n        {\n            \"fullUrl\": \"urn:uuid:7EB02341-5F62-4A76-2CD3-34F523452356\",\n            \"resource\": {\n                \"resourceType\": \"Bundle\",\n                \"id\": \"79FDB414-FADE-459C-87E5-312E646A1910\",\n                \"identifier\": {\n                    \"system\": \"urn:oid:2.16.840.1.113883.2.1.3.2.4.18.8\",\n                    \"value\": \"2BE1EA-L36920-0353AW\"\n                },\n                \"type\": \"collection\",\n                \"entry\": [\n                    {\n                        \"fullUrl\": \"urn:uuid:7B38DE32-877F-6D53-D27C-86E1BA35016C\",\n                        \"resource\": {\n                            \"resourceType\": \"MedicationRequest\",\n                            \"id\": \"7B38DE32-877F-6D53-D27C-86E1BA35016C\",\n                            \"status\": \"active\",\n                            \"intent\": \"order\",\n                            \"medicationCodeableConcept\": {\n                                \"coding\": [\n                                    {\n                                        \"system\": \"http://snomed.info/sct\",\n                                        \"code\": \"317896006\",\n                                        \"display\": \"Digoxin 125 microgram oral tablet\"\n                                    }\n                                ]\n                            },\n                            \"subject\": {\n                                \"reference\": \"urn:uuid:C6750CAA-3CA9-4F29-A282-6EE1AA5D7D4C\"\n                            },\n                            \"encounter\": {\n                                \"reference\": \"urn:uuid:401AEEE1-0E1B-42A0-989C-03DEA8667CB7\"\n                            },\n                            \"authoredOn\": \"2008-02-27T11:38:00+00:00\",\n                            \"requester\": {\n                                \"reference\": \"urn:uuid:1557E58E-3B1E-41DD-B3B5-D4D393DC5A3D\"\n                            },\n                            \"dosageInstruction\": [\n                                {\n                                    \"text\": \"1 tablet after breakfast\"\n                                }\n                            ],\n                            \"dispenseRequest\": {\n                                \"quantity\": {\n                                    \"value\": 28,\n                                    \"unit\": \"tablet\",\n                                    \"system\": \"http://snomed.info/sct\",\n                                    \"code\": \"3319411000001109\"\n                                }\n                            }\n                        }\n                    },\n                    {\n                        \"fullUrl\": \"urn:uuid:8D12DE62-826F-8D32-E17C-86D3BA56013E\",\n                        \"resource\": {\n                            \"resourceType\": \"MedicationRequest\",\n                            \"id\": \"8D12DE62-826F-8D32-E17C-86D3BA56013E\",\n                            \"status\": \"active\",\n                            \"intent\": \"order\",\n                            \"medicationCodeableConcept\": {\n                                \"coding\": [\n                                    {\n                                        \"system\": \"http://snomed.info/sct\",\n                                        \"code\": \"319775004\",\n                                        \"display\": \"Aspirin 75 mg oral tablet\"\n                                    }\n                                ]\n                            },\n                            \"subject\": {\n                                \"reference\": \"urn:uuid:C6750CAA-3CA9-4F29-A282-6EE1AA5D7D4C\"\n                            },\n                            \"encounter\": {\n                                \"reference\": \"urn:uuid:401AEEE1-0E1B-42A0-989C-03DEA8667CB7\"\n                            },\n                            \"authoredOn\": \"2008-02-27T11:38:00+00:00\",\n                            \"requester\": {\n                                \"reference\": \"urn:uuid:1557E58E-3B1E-41DD-B3B5-D4D393DC5A3D\"\n                            },\n                            \"dosageInstruction\": [\n                                {\n                                    \"text\": \"1 tablet during breakfast\"\n                                }\n                            ],\n                            \"dispenseRequest\": {\n                                \"quantity\": {\n                                    \"value\": 28,\n                                    \"unit\": \"tablet\",\n                                    \"system\": \"http://snomed.info/sct\",\n                                    \"code\": \"3319411000001109\"\n                                }\n                            }\n                        }\n                    },\n                    {\n                        \"fullUrl\": \"urn:uuid:9A12DE62-826F-8D32-E17C-86D3BA56023F\",\n                        \"resource\": {\n                            \"resourceType\": \"MedicationRequest\",\n                            \"id\": \"9A12DE62-826F-8D32-E17C-86D3BA56023F\",\n                            \"status\": \"active\",\n                            \"intent\": \"order\",\n                            \"medicationCodeableConcept\": {\n                                \"coding\": [\n                                    {\n                                        \"system\": \"http://snomed.info/sct\",\n                                        \"code\": \"377145005\",\n                                        \"display\": \"Lorazepam 2 mg oral tablet\"\n                                    }\n                                ]\n                            },\n                            \"subject\": {\n                                \"reference\": \"urn:uuid:C6750CAA-3CA9-4F29-A282-6EE1AA5D7D4C\"\n                            },\n                            \"encounter\": {\n                                \"reference\": \"urn:uuid:401AEEE1-0E1B-42A0-989C-03DEA8667CB7\"\n                            },\n                            \"authoredOn\": \"2008-02-27T11:38:00+00:00\",\n                            \"requester\": {\n                                \"reference\": \"urn:uuid:1557E58E-3B1E-41DD-B3B5-D4D393DC5A3D\"\n                            },\n                            \"dosageInstruction\": [\n                                {\n                                    \"text\": \"3 tablets before breakfast\"\n                                }\n                            ],\n                            \"dispenseRequest\": {\n                                \"quantity\": {\n                                    \"value\": 84,\n                                    \"unit\": \"tablet\",\n                                    \"system\": \"http://snomed.info/sct\",\n                                    \"code\": \"3319411000001109\"\n                                }\n                            }\n                        }\n                    },\n                    {\n                        \"fullUrl\": \"urn:uuid:2A32DE62-826F-8D32-E17C-86D3BA56013D\",\n                        \"resource\": {\n                            \"resourceType\": \"MedicationRequest\",\n                            \"id\": \"2A32DE62-826F-8D32-E17C-86D3BA56013D\",\n                            \"status\": \"active\",\n                            \"intent\": \"order\",\n                            \"medicationCodeableConcept\": {\n                                \"coding\": [\n                                    {\n                                        \"system\": \"http://snomed.info/sct\",\n                                        \"code\": \"421375004\",\n                                        \"display\": \"Citalopram (as citalopram hydrobromide) 40 mg orodispersible tablet\"\n                                    }\n                                ]\n                            },\n                            \"subject\": {\n                                \"reference\": \"urn:uuid:C6750CAA-3CA9-4F29-A282-6EE1AA5D7D4C\"\n                            },\n                            \"encounter\": {\n                                \"reference\": \"urn:uuid:401AEEE1-0E1B-42A0-989C-03DEA8667CB7\"\n                            },\n                            \"authoredOn\": \"2008-02-27T11:38:00+00:00\",\n                            \"requester\": {\n                                \"reference\": \"urn:uuid:1557E58E-3B1E-41DD-B3B5-D4D393DC5A3D\"\n                            },\n                            \"dosageInstruction\": [\n                                {\n                                    \"text\": \"2 tablets after breakfast\"\n                                }\n                            ],\n                            \"dispenseRequest\": {\n                                \"quantity\": {\n                                    \"value\": 56,\n                                    \"unit\": \"tablet\",\n                                    \"system\": \"http://snomed.info/sct\",\n                                    \"code\": \"3319411000001109\"\n                                }\n                            }\n                        }\n                    },\n                    {\n                        \"fullUrl\": \"urn:uuid:C6750CAA-3CA9-4F29-A282-6EE1AA5D7D4C\",\n                        \"resource\": {\n                            \"resourceType\": \"Patient\",\n                            \"id\": \"C6750CAA-3CA9-4F29-A282-6EE1AA5D7D4C\",\n                            \"identifier\": [\n                                {\n                                    \"system\": \"https://fhir.nhs.uk/Id/nhs-number\",\n                                    \"value\": \"9900008464\"\n                                }\n                            ],\n                            \"name\": [\n                                {\n                                    \"use\": \"official\",\n                                    \"family\": \"Anderson\",\n                                    \"given\": [\n                                        \"Michael\",\n                                        \"Jack\"\n                                    ],\n                                    \"prefix\": [\n                                        \"Mr\"\n                                    ]\n                                }\n                            ],\n                            \"gender\": \"male\",\n                            \"birthDate\": \"1973-04-21\",\n                            \"address\": [\n                                {\n                                    \"use\": \"home\",\n                                    \"type\": \"both\",\n                                    \"line\": [\n                                        \"1 Otley Road,\"\n                                    ],\n                                    \"city\": \"Leeds\",\n                                    \"postalCode\": \"LS6 5RU\"\n                                }\n                            ]\n                        }\n                    },\n                    {\n                        \"fullUrl\": \"urn:uuid:1557E58E-3B1E-41DD-B3B5-D4D393DC5A3D\",\n                        \"resource\": {\n                            \"resourceType\": \"Practitioner\",\n                            \"id\": \"1557E58E-3B1E-41DD-B3B5-D4D393DC5A3D\",\n                            \"identifier\": [\n                                {\n                                    \"system\": \"https://fhir.nhs.uk/Id/sds-user-id\",\n                                    \"value\": \"125686540025\"\n                                },\n                                {\n                                    \"system\": \"https://fhir.nhs.uk/Id/sds-job-role-id\",\n                                    \"value\": \"R0260\"\n                                },\n                                {\n                                    \"system\": \"https://fhir.nhs.uk/Id/sds-role-profile-id\",\n                                    \"value\": \"934565838956\"\n                                }\n                            ],\n                            \"name\": [\n                                {\n                                    \"use\": \"official\",\n                                    \"family\": \"Hurst\",\n                                    \"prefix\": [\n                                        \"Dr\"\n                                    ]\n                                }\n                            ],\n                            \"telecom\": [\n                                {\n                                    \"system\": \"phone\",\n                                    \"value\": \"tel:011327534256\",\n                                    \"use\": \"work\"\n                                }\n                            ]\n                        }\n                    },\n                    {\n                        \"fullUrl\": \"urn:uuid:401AEEE1-0E1B-42A0-989C-03DEA8667CB7\",\n                        \"resource\": {\n                            \"resourceType\": \"Encounter\",\n                            \"id\": \"401AEEE1-0E1B-42A0-989C-03DEA8667CB7\",\n                            \"status\": \"finished\",\n                            \"class\": {\n                                \"system\": \"http://terminology.hl7.org/CodeSystem/v3-ActCode\",\n                                \"code\": \"AMB\"\n                            },\n                            \"serviceProvider\": {\n                                \"reference\": \"urn:uuid:6666C3B3-FDCD-41B8-9D69-AD1E6D99D9FC\"\n                            }\n                        }\n                    },\n                    {\n                        \"fullUrl\": \"urn:uuid:6666C3B3-FDCD-41B8-9D69-AD1E6D99D9FC\",\n                        \"resource\": {\n                            \"resourceType\": \"Organization\",\n                            \"id\": \"6666C3B3-FDCD-41B8-9D69-AD1E6D99D9FC\",\n                            \"identifier\": [\n                                {\n                                    \"system\": \"https://fhir.nhs.uk/Id/ods-organization-code\",\n                                    \"value\": \"M85011\"\n                                }\n                            ],\n                            \"type\": [\n                                {\n                                    \"coding\": [\n                                        {\n                                            \"system\": \"urn:oid:2.16.840.1.113883.2.1.3.2.4.17.94\",\n                                            \"code\": \"001\",\n                                            \"display\": \"General Medical Practice\"\n                                        }\n                                    ]\n                                }\n                            ],\n                            \"name\": \"Signing_Surg_1\",\n                            \"telecom\": [\n                                {\n                                    \"system\": \"phone\",\n                                    \"value\": \"tel:01132754568\",\n                                    \"use\": \"work\"\n                                }\n                            ],\n                            \"address\": [\n                                {\n                                    \"use\": \"work\",\n                                    \"line\": [\n                                        \"1 Princes Street\"\n                                    ],\n                                    \"city\": \"Leeds\",\n                                    \"postalCode\": \"LS1 5AH\"\n                                }\n                            ],\n                            \"partOf\": {\n                                \"reference\": \"urn:uuid:8DCB2153-09F5-4604-9229-A5C8C7195199\"\n                            }\n                        }\n                    },\n                    {\n                        \"fullUrl\": \"urn:uuid:8DCB2153-09F5-4604-9229-A5C8C7195199\",\n                        \"resource\": {\n                            \"resourceType\": \"Organization\",\n                            \"id\": \"8DCB2153-09F5-4604-9229-A5C8C7195199\",\n                            \"identifier\": [\n                                {\n                                    \"system\": \"https://fhir.nhs.uk/Id/ods-organization-code\",\n                                    \"value\": \"4CD\"\n                                }\n                            ],\n                            \"type\": [\n                                {\n                                    \"coding\": [\n                                        {\n                                            \"system\": \"urn:oid:2.16.840.1.113883.2.1.3.2.4.17.94\",\n                                            \"code\": \"005\",\n                                            \"display\": \"Primary Care Trust\"\n                                        }\n                                    ]\n                                }\n                            ],\n                            \"name\": \"West Yorkshire\"\n                        }\n                    }\n                ]\n            }\n        },\n        {\n            \"fullUrl\": \"urn:uuid:28828C55-8FA7-42D7-916F-FCF076E0C10E\",\n            \"resource\": {\n                \"resourceType\": \"Provenance\",\n                \"id\": \"28828C55-8FA7-42D7-916F-FCF076E0C10E\",\n                \"target\": [\n                    {\n                        \"reference\": \"urn:uuid:7EB02341-5F62-4A76-2CD3-34F523452356\"\n                    }\n                ],\n                \"recorded\": \"2008-02-27T11:38:00+00:00\",\n                \"agent\": [\n                    {\n                        \"who\": {\n                            \"reference\": \"urn:uuid:1557E58E-3B1E-41DD-B3B5-D4D393DC5A3D\"\n                        }\n                    }\n                ],\n                \"signature\": [\n                    {\n                        \"type\": [\n                            {\n                                \"system\": \"urn:iso-astm:E1762-95:2013\",\n                                \"code\": \"1.2.840.10065.1.12.1.1\"\n                            }\n                        ],\n                        \"when\": \"2008-02-27T11:38:00+00:00\",\n                        \"who\": {\n                            \"reference\": \"urn:uuid:1557E58E-3B1E-41DD-B3B5-D4D393DC5A3D\"\n                        },\n                        \"data\": \"sHu+ug41w5rWgcrogjKPe6JQcy5AodR/2pMJG1Lx+WDf6osgt6GsZuavbowqSh7RI79NUCMb0/Po3P5JGSiIEzFfWvdix7twyN8BhRJzZVoz4nY++roq6th1cZMUtm+ttEMMQhLVFY4hFZrZqZuMhsq5i2m4RCvS+IL4RMH6Hnc=\"\n                    }\n                ]\n            }\n        },\n        {\n            \"fullUrl\": \"urn:uuid:1557E58E-3B1E-41DD-B3B5-D4D393DC5A3D\",\n            \"resource\": {\n                \"resourceType\": \"Practitioner\",\n                \"id\": \"1557E58E-3B1E-41DD-B3B5-D4D393DC5A3D\",\n                \"identifier\": [\n                    {\n                        \"system\": \"https://fhir.nhs.uk/Id/sds-user-id\",\n                        \"value\": \"125686540025\"\n                    },\n                    {\n                        \"system\": \"https://fhir.nhs.uk/Id/sds-job-role-id\",\n                        \"value\": \"R0260\"\n                    },\n                    {\n                        \"system\": \"https://fhir.nhs.uk/Id/sds-role-profile-id\",\n                        \"value\": \"934565838956\"\n                    }\n                ],\n                \"name\": [\n                    {\n                        \"use\": \"official\",\n                        \"family\": \"Hurst\",\n                        \"prefix\": [\n                            \"Dr\"\n                        ]\n                    }\n                ],\n                \"telecom\": [\n                    {\n                        \"system\": \"phone\",\n                        \"value\": \"tel:011327534256\",\n                        \"use\": \"work\"\n                    }\n                ]\n            }\n        }\n    ]\n}",
              "pm.test(\"Status code is 200\", function () {",
              "    pm.response.to.have.status(200);",
              "});",
              "pm.test(\"Body is correct\", function () {",
              "    pm.response.to.have.body(responseText);",
              "});"
            ],
            "type": "text/javascript"
          }
        }
      ],
      "request": {
        "auth": {
          "type": "oauth2",
          "oauth2": [
            {
              "key": "accessToken",
              "value": "",
              "type": "string"
            },
            {
              "key": "tokenType",
              "value": "Bearer",
              "type": "string"
            },
            {
              "key": "addTokenTo",
              "value": "header",
              "type": "string"
            }
          ]
        },
        "method": "PUT",
        "header": [
          {
            "key": "NHSD-Session-URID",
            "type": "text",
            "value": "123"
          }
        ],
        "body": {
          "mode": "raw",
          "raw": "{\n  \"resourceType\": \"Bundle\",\n  \"id\": \"E8E8D623-62C9-4642-BC51-AB50430DF8CA\",\n  \"type\": \"collection\",\n  \"entry\": [\n    {\n      \"fullUrl\": \"urn:uuid:7EB02341-5F62-4A76-2CD3-34F523452356\",\n      \"resource\": {\n        \"resourceType\": \"Bundle\",\n        \"id\": \"7EB02341-5F62-4A76-2CD3-34F523452356\",\n        \"type\": \"collection\",\n        \"entry\": [\n          {\n            \"fullUrl\": \"urn:uuid:7B38DE32-877F-6D53-D27C-86E1BA35016C\",\n            \"resource\": {\n              \"resourceType\": \"MedicationRequest\",\n              \"id\": \"7B38DE32-877F-6D53-D27C-86E1BA35016C\",\n              \"status\": \"active\",\n              \"intent\": \"order\",\n              \"medicationCodeableConcept\": {\n                \"coding\": [\n                  {\n                    \"system\": \"http://snomed.info/sct\",\n                    \"code\": \"317896006\",\n                    \"display\": \"Digoxin 125 microgram oral tablet\"\n                  }\n                ]\n              },\n              \"subject\": {\n                \"reference\": \"urn:uuid:C6750CAA-3CA9-4F29-A282-6EE1AA5D7D4C\"\n              },\n              \"encounter\": {\n                \"reference\": \"urn:uuid:401AEEE1-0E1B-42A0-989C-03DEA8667CB7\"\n              },\n              \"authoredOn\": \"2008-02-27T11:38:00+00:00\",\n              \"requester\": {\n                \"reference\": \"urn:uuid:1557E58E-3B1E-41DD-B3B5-D4D393DC5A3D\"\n              },\n              \"dosageInstruction\": [\n                {\n                  \"text\": \"1 tablet after breakfast\"\n                }\n              ],\n              \"dispenseRequest\": {\n                \"quantity\": {\n                  \"value\": 28,\n                  \"unit\": \"tablet\",\n                  \"system\": \"http://snomed.info/sct\",\n                  \"code\": \"3319411000001109\"\n                }\n              }\n            }\n          },\n          {\n            \"fullUrl\": \"urn:uuid:8D12DE62-826F-8D32-E17C-86D3BA56013E\",\n            \"resource\": {\n              \"resourceType\": \"MedicationRequest\",\n              \"id\": \"8D12DE62-826F-8D32-E17C-86D3BA56013E\",\n              \"status\": \"active\",\n              \"intent\": \"order\",\n              \"medicationCodeableConcept\": {\n                \"coding\": [\n                  {\n                    \"system\": \"http://snomed.info/sct\",\n                    \"code\": \"319775004\",\n                    \"display\": \"Aspirin 75 mg oral tablet\"\n                  }\n                ]\n              },\n              \"subject\": {\n                \"reference\": \"urn:uuid:C6750CAA-3CA9-4F29-A282-6EE1AA5D7D4C\"\n              },\n              \"encounter\": {\n                \"reference\": \"urn:uuid:401AEEE1-0E1B-42A0-989C-03DEA8667CB7\"\n              },\n              \"authoredOn\": \"2008-02-27T11:38:00+00:00\",\n              \"requester\": {\n                \"reference\": \"urn:uuid:1557E58E-3B1E-41DD-B3B5-D4D393DC5A3D\"\n              },\n              \"dosageInstruction\": [\n                {\n                  \"text\": \"1 tablet during breakfast\"\n                }\n              ],\n              \"dispenseRequest\": {\n                \"quantity\": {\n                  \"value\": 28,\n                  \"unit\": \"tablet\",\n                  \"system\": \"http://snomed.info/sct\",\n                  \"code\": \"3319411000001109\"\n                }\n              }\n            }\n          },\n          {\n            \"fullUrl\": \"urn:uuid:9A12DE62-826F-8D32-E17C-86D3BA56023F\",\n            \"resource\": {\n              \"resourceType\": \"MedicationRequest\",\n              \"id\": \"9A12DE62-826F-8D32-E17C-86D3BA56023F\",\n              \"status\": \"active\",\n              \"intent\": \"order\",\n              \"medicationCodeableConcept\": {\n                \"coding\": [\n                  {\n                    \"system\": \"http://snomed.info/sct\",\n                    \"code\": \"377145005\",\n                    \"display\": \"Lorazepam 2 mg oral tablet\"\n                  }\n                ]\n              },\n              \"subject\": {\n                \"reference\": \"urn:uuid:C6750CAA-3CA9-4F29-A282-6EE1AA5D7D4C\"\n              },\n              \"encounter\": {\n                \"reference\": \"urn:uuid:401AEEE1-0E1B-42A0-989C-03DEA8667CB7\"\n              },\n              \"authoredOn\": \"2008-02-27T11:38:00+00:00\",\n              \"requester\": {\n                \"reference\": \"urn:uuid:1557E58E-3B1E-41DD-B3B5-D4D393DC5A3D\"\n              },\n              \"dosageInstruction\": [\n                {\n                  \"text\": \"3 tablets before breakfast\"\n                }\n              ],\n              \"dispenseRequest\": {\n                \"quantity\": {\n                  \"value\": 84,\n                  \"unit\": \"tablet\",\n                  \"system\": \"http://snomed.info/sct\",\n                  \"code\": \"3319411000001109\"\n                }\n              }\n            }\n          },\n          {\n            \"fullUrl\": \"urn:uuid:2A32DE62-826F-8D32-E17C-86D3BA56013D\",\n            \"resource\": {\n              \"resourceType\": \"MedicationRequest\",\n              \"id\": \"2A32DE62-826F-8D32-E17C-86D3BA56013D\",\n              \"status\": \"active\",\n              \"intent\": \"order\",\n              \"medicationCodeableConcept\": {\n                \"coding\": [\n                  {\n                    \"system\": \"http://snomed.info/sct\",\n                    \"code\": \"421375004\",\n                    \"display\": \"Citalopram (as citalopram hydrobromide) 40 mg orodispersible tablet\"\n                  }\n                ]\n              },\n              \"subject\": {\n                \"reference\": \"urn:uuid:C6750CAA-3CA9-4F29-A282-6EE1AA5D7D4C\"\n              },\n              \"encounter\": {\n                \"reference\": \"urn:uuid:401AEEE1-0E1B-42A0-989C-03DEA8667CB7\"\n              },\n              \"authoredOn\": \"2008-02-27T11:38:00+00:00\",\n              \"requester\": {\n                \"reference\": \"urn:uuid:1557E58E-3B1E-41DD-B3B5-D4D393DC5A3D\"\n              },\n              \"dosageInstruction\": [\n                {\n                  \"text\": \"2 tablets after breakfast\"\n                }\n              ],\n              \"dispenseRequest\": {\n                \"quantity\": {\n                  \"value\": 56,\n                  \"unit\": \"tablet\",\n                  \"system\": \"http://snomed.info/sct\",\n                  \"code\": \"3319411000001109\"\n                }\n              }\n            }\n          },\n          {\n            \"fullUrl\": \"urn:uuid:C6750CAA-3CA9-4F29-A282-6EE1AA5D7D4C\",\n            \"resource\": {\n              \"resourceType\": \"Patient\",\n              \"id\": \"C6750CAA-3CA9-4F29-A282-6EE1AA5D7D4C\",\n              \"identifier\": [\n                {\n                  \"system\": \"https://fhir.nhs.uk/Id/nhs-number\",\n                  \"value\": \"9900008464\"\n                }\n              ],\n              \"name\": [\n                {\n                  \"use\": \"official\",\n                  \"family\": \"Anderson\",\n                  \"given\": [\n                    \"Michael\",\n                    \"Jack\"\n                  ],\n                  \"prefix\": [\n                    \"Mr\"\n                  ]\n                }\n              ],\n              \"gender\": \"male\",\n              \"birthDate\": \"1973-04-21\",\n              \"address\": [\n                {\n                  \"use\": \"home\",\n                  \"type\": \"both\",\n                  \"line\": [\n                    \"1 Otley Road,\"\n                  ],\n                  \"city\": \"Leeds\",\n                  \"postalCode\": \"LS6 5RU\"\n                }\n              ]\n            }\n          },\n          {\n            \"fullUrl\": \"urn:uuid:1557E58E-3B1E-41DD-B3B5-D4D393DC5A3D\",\n            \"resource\": {\n              \"resourceType\": \"Practitioner\",\n              \"id\": \"1557E58E-3B1E-41DD-B3B5-D4D393DC5A3D\",\n              \"identifier\": [\n                {\n                  \"system\": \"https://fhir.nhs.uk/Id/sds-user-id\",\n                  \"value\": \"125686540025\"\n                },\n                {\n                  \"system\": \"https://fhir.nhs.uk/Id/sds-job-role-id\",\n                  \"value\": \"R0260\"\n                },\n                {\n                  \"system\": \"https://fhir.nhs.uk/Id/sds-role-profile-id\",\n                  \"value\": \"934565838956\"\n                }\n              ],\n              \"name\": [\n                {\n                  \"use\": \"official\",\n                  \"family\": \"Hurst\",\n                  \"prefix\": [\n                    \"Dr\"\n                  ]\n                }\n              ],\n              \"telecom\": [\n                {\n                  \"system\": \"phone\",\n                  \"value\": \"tel:011327534256\",\n                  \"use\": \"work\"\n                }\n              ]\n            }\n          },\n          {\n            \"fullUrl\": \"urn:uuid:401AEEE1-0E1B-42A0-989C-03DEA8667CB7\",\n            \"resource\": {\n              \"resourceType\": \"Encounter\",\n              \"id\": \"401AEEE1-0E1B-42A0-989C-03DEA8667CB7\",\n              \"status\": \"finished\",\n              \"class\": {\n                \"system\": \"http://terminology.hl7.org/CodeSystem/v3-ActCode\",\n                \"code\": \"AMB\"\n              },\n              \"serviceProvider\": {\n                \"reference\": \"urn:uuid:6666C3B3-FDCD-41B8-9D69-AD1E6D99D9FC\"\n              }\n            }\n          },\n          {\n            \"fullUrl\": \"urn:uuid:6666C3B3-FDCD-41B8-9D69-AD1E6D99D9FC\",\n            \"resource\": {\n              \"resourceType\": \"Organization\",\n              \"id\": \"6666C3B3-FDCD-41B8-9D69-AD1E6D99D9FC\",\n              \"identifier\": [\n                {\n                  \"system\": \"https://fhir.nhs.uk/Id/ods-organization-code\",\n                  \"value\": \"M85011\"\n                }\n              ],\n              \"type\": [\n                {\n                  \"coding\": [\n                    {\n                      \"system\": \"urn:oid:2.16.840.1.113883.2.1.3.2.4.17.94\",\n                      \"code\": \"001\",\n                      \"display\": \"General Medical Practice\"\n                    }\n                  ]\n                }\n              ],\n              \"name\": \"Signing_Surg_1\",\n              \"telecom\": [\n                {\n                  \"system\": \"phone\",\n                  \"value\": \"tel:01132754568\",\n                  \"use\": \"work\"\n                }\n              ],\n              \"address\": [\n                {\n                  \"use\": \"work\",\n                  \"line\": [\n                    \"1 Princes Street\"\n                  ],\n                  \"city\": \"Leeds\",\n                  \"postalCode\": \"LS1 5AH\"\n                }\n              ],\n              \"partOf\": {\n                \"reference\": \"urn:uuid:8DCB2153-09F5-4604-9229-A5C8C7195199\"\n              }\n            }\n          },\n          {\n            \"fullUrl\": \"urn:uuid:8DCB2153-09F5-4604-9229-A5C8C7195199\",\n            \"resource\": {\n              \"resourceType\": \"Organization\",\n              \"id\": \"8DCB2153-09F5-4604-9229-A5C8C7195199\",\n              \"identifier\": [\n                {\n                  \"system\": \"https://fhir.nhs.uk/Id/ods-organization-code\",\n                  \"value\": \"4CD\"\n                }\n              ],\n              \"type\": [\n                {\n                  \"coding\": [\n                    {\n                      \"system\": \"urn:oid:2.16.840.1.113883.2.1.3.2.4.17.94\",\n                      \"code\": \"005\",\n                      \"display\": \"Primary Care Trust\"\n                    }\n                  ]\n                }\n              ],\n              \"name\": \"West Yorkshire\"\n            }\n          }\n        ]\n      }\n    },\n    {\n      \"fullUrl\": \"urn:uuid:28828C55-8FA7-42D7-916F-FCF076E0C10E\",\n      \"resource\": {\n        \"resourceType\": \"Provenance\",\n        \"id\": \"28828C55-8FA7-42D7-916F-FCF076E0C10E\",\n        \"target\": [\n          {\n            \"reference\": \"urn:uuid:7EB02341-5F62-4A76-2CD3-34F523452356\"\n          }\n        ],\n        \"recorded\": \"2008-02-27T11:38:00+00:00\",\n        \"agent\": [\n          {\n            \"who\": {\n              \"reference\": \"urn:uuid:1557E58E-3B1E-41DD-B3B5-D4D393DC5A3D\"\n            }\n          }\n        ],\n        \"signature\": [\n          {\n            \"type\": [\n              {\n                \"system\": \"urn:iso-astm:E1762-95:2013\",\n                \"code\": \"1.2.840.10065.1.12.1.1\"\n              }\n            ],\n            \"when\": \"2008-02-27T11:38:00+00:00\",\n            \"who\": {\n              \"reference\": \"urn:uuid:1557E58E-3B1E-41DD-B3B5-D4D393DC5A3D\"\n            },\n            \"data\": \"sHu+ug41w5rWgcrogjKPe6JQcy5AodR/2pMJG1Lx+WDf6osgt6GsZuavbowqSh7RI79NUCMb0/Po3P5JGSiIEzFfWvdix7twyN8BhRJzZVoz4nY++roq6th1cZMUtm+ttEMMQhLVFY4hFZrZqZuMhsq5i2m4RCvS+IL4RMH6Hnc=\"\n          }\n        ]\n      }\n    },\n    {\n      \"fullUrl\": \"urn:uuid:1557E58E-3B1E-41DD-B3B5-D4D393DC5A3D\",\n      \"resource\": {\n        \"resourceType\": \"Practitioner\",\n        \"id\": \"1557E58E-3B1E-41DD-B3B5-D4D393DC5A3D\",\n        \"identifier\": [\n          {\n            \"system\": \"https://fhir.nhs.uk/Id/sds-user-id\",\n            \"value\": \"125686540025\"\n          },\n          {\n            \"system\": \"https://fhir.nhs.uk/Id/sds-job-role-id\",\n            \"value\": \"R0260\"\n          },\n          {\n            \"system\": \"https://fhir.nhs.uk/Id/sds-role-profile-id\",\n            \"value\": \"934565838956\"\n          }\n        ],\n        \"name\": [\n          {\n            \"use\": \"official\",\n            \"family\": \"Hurst\",\n            \"prefix\": [\n              \"Dr\"\n            ]\n          }\n        ],\n        \"telecom\": [\n          {\n            \"system\": \"phone\",\n            \"value\": \"tel:011327534256\",\n            \"use\": \"work\"\n          }\n        ]\n      }\n    }\n  ]\n}",
          "options": {
            "raw": {
              "language": "json"
            }
          }
        },
        "url": {
          "raw": "{{base_url}}/Prescription",
          "host": [
            "{{base_url}}"
          ],
          "path": [
            "Prescription"
          ]
        }
      },
      "response": []
    }
  ],
  "protocolProfileBehavior": {}
}
